leakybucket/__init__.py
leakybucket/bucket.py
leakybucket/decorators.py
leakybucket/persistence/__init__.py
leakybucket/persistence/base.py
leakybucket/persistence/memory.py
leakybucket/persistence/redis.py
leakybucket/persistence/sqlite.py
leaky_bucket_py-0.1.3.dist-info/LICENSE
leaky_bucket_py-0.1.3.dist-info/METADATA
leaky_bucket_py-0.1.3.dist-info/WHEEL
leaky_bucket_py-0.1.3.dist-info/top_level.txt
leaky_bucket_py-0.1.3.dist-info/RECORD
