Metadata-Version: 2.1
Name: leaky-bucket-py
Version: 0.1.3
Summary: Leaky bucket implementation in python with different persistence options
Author: DuneRaccoon
Author-email: DuneRaccoon <benjamincsherro@hotmail.com>
License: MIT License
Keywords: rate-limiter,asyncio,leaky-bucket,redis,sqlite3
Classifier: Programming Language :: Python :: 3
Classifier: License :: OSI Approved :: MIT License
Classifier: Programming Language :: Python :: 3.7
Classifier: Programming Language :: Python :: 3.8
Classifier: Programming Language :: Python :: 3.9
Classifier: Programming Language :: Python :: 3.10
Classifier: Programming Language :: Python :: 3.11
Requires-Python: >=3.7
License-File: LICENSE
Requires-Dist: redis>=3.5.3
